pipscope.py
pipscope-0.1.0.dist-info/METADATA
pipscope-0.1.0.dist-info/WHEEL
pipscope-0.1.0.dist-info/entry_points.txt
pipscope-0.1.0.dist-info/RECORD
