Metadata-Version: 2.4
Name: pipscope
Version: 0.1.0
Summary: Interactive TUI for exploring installed Python packages
Project-URL: Homepage, https://github.com/yourusername/pipscope
Project-URL: Repository, https://github.com/yourusername/pipscope
Author-email: Your Name <you@example.com>
License-Expression: MIT
Keywords: packages,pip,terminal,textual,tui
Classifier: Development Status :: 4 - Beta
Classifier: Environment :: Console
Classifier: Intended Audience :: Developers
Classifier: License :: OSI Approved :: MIT License
Classifier: Operating System :: OS Independent
Classifier: Programming Language :: Python :: 3
Classifier: Programming Language :: Python :: 3.9
Classifier: Programming Language :: Python :: 3.10
Classifier: Programming Language :: Python :: 3.11
Classifier: Programming Language :: Python :: 3.12
Classifier: Topic :: Software Development :: Libraries :: Python Modules
Classifier: Topic :: System :: Systems Administration
Requires-Python: >=3.9
Requires-Dist: textual>=0.47.0
